ftp_loader/__init__.py
ftp_loader/loader.py
ftp_loader/main.py
ftp_loader-0.2.2.dist-info/LICENSE.txt
ftp_loader-0.2.2.dist-info/METADATA
ftp_loader-0.2.2.dist-info/WHEEL
ftp_loader-0.2.2.dist-info/entry_points.txt
ftp_loader-0.2.2.dist-info/top_level.txt
ftp_loader-0.2.2.dist-info/RECORD
