Metadata-Version: 2.1
Name: ftp-loader
Version: 0.2.2
Summary: A package to download project data files from FTP
Home-page: https://github.com/rorni/ftp-loader
Author: Roman Rodionov
License: UNKNOWN
Platform: UNKNOWN
Classifier: Programming Language :: Python :: 3
Classifier: License :: OSI Approved :: MIT License
Requires-Python: >=3.5
License-File: LICENSE.txt
Requires-Dist: pysftp (>=0.2.9)
Requires-Dist: tomlkit (>=0.6.0)
